setup.cfg
setup.py
cisco_pass/__init__.py
cisco_pass/password.py
cisco_pass.egg-info/PKG-INFO
cisco_pass.egg-info/SOURCES.txt
cisco_pass.egg-info/dependency_links.txt
cisco_pass.egg-info/requires.txt
cisco_pass.egg-info/top_level.txt