Metadata-Version: 1.1
Name: cisco-pass
Version: 0.1
Summary: Generate Cisco password strings.  Decrypt type7.  Devices: IOS, NXOS, ACE, CatOS
Home-page: https://github.com/rcaldwel/cisco_pass
Author: Roger Caldwell
Author-email: roger@monkey.net
License: UNKNOWN
Download-URL: https://github.com/rcaldwel/cisco_pass/tarball/0.1
Keywords: cisco,password,crypt
Platform: UNKNOWN
